AUTHORS.rst
CONTRIBUTING.rst
HISTORY.rst
LICENSE
MANIFEST.in
README.rst
setup.cfg
setup.py
calculator_tc2/__init__.py
calculator_tc2/calculator_tc2.py
calculator_tc2/cli.py
calculator_tc2.egg-info/PKG-INFO
calculator_tc2.egg-info/SOURCES.txt
calculator_tc2.egg-info/dependency_links.txt
calculator_tc2.egg-info/entry_points.txt
calculator_tc2.egg-info/not-zip-safe
calculator_tc2.egg-info/requires.txt
calculator_tc2.egg-info/top_level.txt
docs/Makefile
docs/authors.rst
docs/conf.py
docs/contributing.rst
docs/history.rst
docs/index.rst
docs/installation.rst
docs/make.bat
docs/readme.rst
docs/usage.rst
tests/__init__.py
tests/test_calculator_tc2.py